asyncio_executor.py
asyncio_executor-0.0.4.data/data/requirements/requirements.txt
asyncio_executor-0.0.4.data/data/requirements/requirements_dev.txt
asyncio_executor-0.0.4.data/data/requirements/requirements_test.txt
asyncio_executor-0.0.4.dist-info/DESCRIPTION.rst
asyncio_executor-0.0.4.dist-info/METADATA
asyncio_executor-0.0.4.dist-info/RECORD
asyncio_executor-0.0.4.dist-info/WHEEL
asyncio_executor-0.0.4.dist-info/metadata.json
asyncio_executor-0.0.4.dist-info/top_level.txt
