Metadata-Version: 2.0
Name: asyncio-executor
Version: 0.0.4
Summary: asyncio-executor
Home-page: https://github.com/Python-Tools/asyncio-executor
Author: hsz
Author-email: hsz1273327@gmail.com
License: MIT
Keywords: asyncio,executor
Platform: UNKNOWN
Classifier: Development Status :: 3 - Alpha
Classifier: Intended Audience :: Developers
Classifier: License :: OSI Approved :: MIT License
Classifier: Programming Language :: Python :: 3.5
Classifier: Programming Language :: Python :: 3.6
Classifier: Topic :: Documentation :: Sphinx
Provides-Extra: dev
Requires-Dist: wheel; extra == 'dev'
Provides-Extra: test
Requires-Dist: coverage; extra == 'test'
Requires-Dist: mypy; extra == 'test'
Requires-Dist: mypy-extensions; extra == 'test'
Requires-Dist: lxml; extra == 'test'
